rtmidi/version.py
rtmidi/midiconstants.py
rtmidi/__init__.py
rtmidi/_rtmidi.cpython-38-darwin.so
rtmidi/midiutil.py
python_rtmidi-1.5.6.dist-info/LICENSE.md
python_rtmidi-1.5.6.dist-info/RECORD
python_rtmidi-1.5.6.dist-info/WHEEL
python_rtmidi-1.5.6.dist-info/METADATA
