Metadata-Version: 2.1
Name: python-rtmidi
Version: 1.5.6
Summary: A Python binding for the RtMidi C++ library implemented using Cython.
Keywords: MIDI multimedia music rtmidi
Author-Email: Christopher Arndt <info@chrisarndt.de>
License: Copyright & License
Classifier: Development Status :: 5 - Production/Stable
Classifier: Environment :: MacOS X
Classifier: Environment :: Win32 (MS Windows)
Classifier: Environment :: Console
Classifier: Intended Audience :: Developers
Classifier: License :: OSI Approved :: MIT License
Classifier: Operating System :: Microsoft :: Windows
Classifier: Operating System :: POSIX
Classifier: Operating System :: MacOS :: MacOS X
Classifier: Programming Language :: Python
Classifier: Programming Language :: Python :: 3
Classifier: Programming Language :: Python :: 3.8
Classifier: Programming Language :: Python :: 3.9
Classifier: Programming Language :: Python :: 3.10
Classifier: Programming Language :: Python :: 3.11
Classifier: Topic :: Multimedia :: Sound/Audio :: MIDI
Classifier: Topic :: Software Development :: Libraries :: Python Modules
Project-URL: Bug tracker, https://github.com/SpotlightKid/python-rtmidi/issues
Project-URL: Documentation, https://spotlightkid.github.io/python-rtmidi/
Project-URL: Download, https://pypi.python.org/pypi/python-rtmidi
Project-URL: Homepage, https://github.com/SpotlightKid/python-rtmidi
Project-URL: Source, https://gitlab.com/SpotlightKid/python-rtmidi/
Requires-Python: >=3.8
